{
  "name": "Plickr",
  "integrations": {
    "cordova": {}
  },
  "type": "angular",
  "/api": {
    "target": "http://localhost:8080/Plickr-war/Resources",
    "secure": false,
    "pathRewrite": {
      "^/api": ""
    }
  },
  "/uploads": {
    "target": "http://localhost:8080/Plickr-war/uploadedFiles",
    "secure": false,
    "pathRewrite": {
      "^/uploads": ""
    }
  },
  "/assets": {
    "target": "http://localhost:8080/Plickr-war",
    "secure": false,
    "pathRewrite": {
      "^/assets": ""
    }
  }
}
